pythonic_schwab_api/__init__.py
pythonic_schwab_api/accounts.py
pythonic_schwab_api/algo_example_script.py
pythonic_schwab_api/api_client.py
pythonic_schwab_api/color_print.py
pythonic_schwab_api/config.py
pythonic_schwab_api/main.py
pythonic_schwab_api/market_data.py
pythonic_schwab_api/multi_terminal.py
pythonic_schwab_api/orders.py
pythonic_schwab_api/stream_client.py
pythonic_schwab_api/stream_utilities.py
pythonic_schwab_api/utilities.py
pythonic_schwab_api-1.0.0.dist-info/LICENSE
pythonic_schwab_api-1.0.0.dist-info/METADATA
pythonic_schwab_api-1.0.0.dist-info/WHEEL
pythonic_schwab_api-1.0.0.dist-info/top_level.txt
pythonic_schwab_api-1.0.0.dist-info/RECORD
