Metadata-Version: 2.1
Name: pythonic_schwab_api
Version: 1.0.0
Summary: This is an unofficial interface to make using the Schwab API easier.
Home-page: https://github.com/Patch-Code-Prosperity/Pythonic-Schwab-API
Author: Cfomodz
License: MIT License
Classifier: Programming Language :: Python :: 3
Classifier: License :: OSI Approved :: MIT License
Classifier: Operating System :: OS Independent
Requires-Python: >=3.7
License-File: LICENSE
Requires-Dist: requests
Requires-Dist: python-dotenv
Requires-Dist: websockets
Requires-Dist: pandas
Requires-Dist: tqdm
